README.md
setup.cfg
setup.py
google_objects/__init__.py
google_objects/auth.py
google_objects/cli.py
google_objects/core.py
google_objects/drive.py
google_objects/sheets.py
google_objects/slides.py
google_objects.egg-info/PKG-INFO
google_objects.egg-info/SOURCES.txt
google_objects.egg-info/dependency_links.txt
google_objects.egg-info/entry_points.txt
google_objects.egg-info/requires.txt
google_objects.egg-info/top_level.txt
tests/__init__.py
tests/drive_test.py
tests/sheets_test.py
tests/slides_test.py
tests/utils.py