Metadata-Version: 1.1
Name: google-objects
Version: 0.0.4
Summary: A simple OO wrapper around google's python API client
Home-page: https://github.com/condad/google-objects
Author: Connor Sullivan
Author-email: sully4792@gmail.com
License: UNKNOWN
Download-URL: https://github.com/condad/google-objects/tarball/0.0.4
Keywords: google api,google sheets,google drive,google slides
Platform: UNKNOWN
Classifier: Development Status :: 3 - Alpha
Classifier: Intended Audience :: Developers
Classifier: License :: OSI Approved :: Apache Software License
Classifier: Operating System :: OS Independent
Classifier: Programming Language :: Python
Classifier: Programming Language :: Python :: 3.5
Classifier: Programming Language :: Python :: 3.6
Classifier: Topic :: Software Development :: Libraries :: Python Modules
